beanllm/__init__.py
beanllm/decorators/__init__.py
beanllm/decorators/error_handler.py
beanllm/decorators/logger.py
beanllm/decorators/validation.py
beanllm/decorators/validation_utils.py
beanllm/domain/__init__.py
beanllm/domain/audio/__init__.py
beanllm/domain/audio/bean_stt.py
beanllm/domain/audio/enums.py
beanllm/domain/audio/models.py
beanllm/domain/audio/types.py
beanllm/domain/audio/engines/__init__.py
beanllm/domain/audio/engines/base.py
beanllm/domain/audio/engines/canary_engine.py
beanllm/domain/audio/engines/distil_whisper_engine.py
beanllm/domain/audio/engines/granite_engine.py
beanllm/domain/audio/engines/moonshine_engine.py
beanllm/domain/audio/engines/parakeet_engine.py
beanllm/domain/audio/engines/sensevoice_engine.py
beanllm/domain/audio/engines/whisper_engine.py
beanllm/domain/embeddings/__init__.py
beanllm/domain/embeddings/advanced.py
beanllm/domain/embeddings/api_embeddings.py
beanllm/domain/embeddings/base.py
beanllm/domain/embeddings/cache.py
beanllm/domain/embeddings/factory.py
beanllm/domain/embeddings/local_embeddings.py
beanllm/domain/embeddings/providers.py
beanllm/domain/embeddings/types.py
beanllm/domain/embeddings/utils.py
beanllm/domain/evaluation/__init__.py
beanllm/domain/evaluation/analytics.py
beanllm/domain/evaluation/base_framework.py
beanllm/domain/evaluation/base_metric.py
beanllm/domain/evaluation/checklist.py
beanllm/domain/evaluation/continuous.py
beanllm/domain/evaluation/deepeval_wrapper.py
beanllm/domain/evaluation/drift_detection.py
beanllm/domain/evaluation/enums.py
beanllm/domain/evaluation/evaluator.py
beanllm/domain/evaluation/factory.py
beanllm/domain/evaluation/human_feedback.py
beanllm/domain/evaluation/hybrid_evaluator.py
beanllm/domain/evaluation/lm_eval_harness_wrapper.py
beanllm/domain/evaluation/metrics.py
beanllm/domain/evaluation/ragas_wrapper.py
beanllm/domain/evaluation/results.py
beanllm/domain/evaluation/rubric.py
beanllm/domain/evaluation/trulens_wrapper.py
beanllm/domain/finetuning/__init__.py
beanllm-0.2.2.dist-info/licenses/LICENSE
beanllm-0.2.2.dist-info/METADATA
beanllm-0.2.2.dist-info/WHEEL
beanllm-0.2.2.dist-info/entry_points.txt
beanllm-0.2.2.dist-info/top_level.txt
beanllm-0.2.2.dist-info/RECORD
