Metadata-Version: 2.4
Name: beanllm
Version: 0.2.2
Summary: Unified toolkit for managing and using multiple LLM providers with automatic model detection
Author-email: leebeanbin <wjdqlsdu388@gmail.com>
License-Expression: MIT
Project-URL: Homepage, https://github.com/leebeanbin/beanllm
Project-URL: Documentation, https://github.com/leebeanbin/beanllm#readme
Project-URL: Repository, https://github.com/leebeanbin/beanllm
Project-URL: Bug Tracker, https://github.com/leebeanbin/beanllm/issues
Keywords: llm,beanllm,ai-toolkit,openai,claude,anthropic,gemini,ollama,ai,machine-learning,rag,langchain,embedding,vector-store,chatbot,gpt,multi-agent,agent,nlp,prompt-engineering
Classifier: Development Status :: 3 - Alpha
Classifier: Intended Audience :: Developers
Classifier: Programming Language :: Python :: 3
Classifier: Programming Language :: Python :: 3.11
Classifier: Programming Language :: Python :: 3.12
Classifier: Topic :: Software Development :: Libraries :: Python Modules
Classifier: Topic :: Scientific/Engineering :: Artificial Intelligence
Requires-Python: >=3.11
License-File: LICENSE
Requires-Dist: httpx<1.0.0,>=0.24.0
Requires-Dist: python-dotenv<2.0.0,>=1.0.0
Requires-Dist: rich<15.0.0,>=13.0.0
Requires-Dist: beautifulsoup4<5.0.0,>=4.12.0
Requires-Dist: requests<3.0.0,>=2.31.0
Requires-Dist: numpy<3.0.0,>=1.24.0
Requires-Dist: tiktoken<1.0.0,>=0.5.0
Requires-Dist: PyMuPDF<2.0.0,>=1.23.0
Requires-Dist: pdfplumber<1.0.0,>=0.10.0
Requires-Dist: pandas<3.0.0,>=2.0.0
Provides-Extra: openai
Requires-Dist: openai<3.0.0,>=1.0.0; extra == "openai"
Provides-Extra: anthropic
Requires-Dist: anthropic<1.0.0,>=0.18.0; extra == "anthropic"
Provides-Extra: gemini
Requires-Dist: google-generativeai<1.0.0,>=0.3.0; extra == "gemini"
Provides-Extra: ollama
Requires-Dist: ollama<1.0.0,>=0.1.0; extra == "ollama"
Provides-Extra: audio
Requires-Dist: openai-whisper<20250626,>=20231117; extra == "audio"
Provides-Extra: ml
Requires-Dist: marker-pdf<2.0.0,>=0.2.0; extra == "ml"
Requires-Dist: torch<3.0.0,>=2.0.0; extra == "ml"
Provides-Extra: all
Requires-Dist: openai<3.0.0,>=1.0.0; extra == "all"
Requires-Dist: anthropic<1.0.0,>=0.18.0; extra == "all"
Requires-Dist: google-generativeai<1.0.0,>=0.3.0; extra == "all"
Requires-Dist: ollama<1.0.0,>=0.1.0; extra == "all"
Requires-Dist: openai-whisper<20250626,>=20231117; extra == "all"
Requires-Dist: marker-pdf<2.0.0,>=0.2.0; extra == "all"
Requires-Dist: torch<3.0.0,>=2.0.0; extra == "all"
Provides-Extra: evaluation
Requires-Dist: apscheduler<4.0.0,>=3.10.0; extra == "evaluation"
Provides-Extra: dev
Requires-Dist: pytest<10.0.0,>=9.0.2; extra == "dev"
Requires-Dist: pytest-asyncio<2.0.0,>=0.21.0; extra == "dev"
Requires-Dist: pytest-cov<5.0.0,>=4.0.0; extra == "dev"
Requires-Dist: black<26.0.0,>=23.0.0; extra == "dev"
Requires-Dist: ruff<1.0.0,>=0.1.0; extra == "dev"
Requires-Dist: mypy<2.0.0,>=1.0.0; extra == "dev"
Dynamic: license-file
